pretix_oidc/__init__.py
pretix_oidc/apps.py
pretix_oidc/auth.py
pretix_oidc/forms.py
pretix_oidc/models.py
pretix_oidc/signals.py
pretix_oidc/urls.py
pretix_oidc/views.py
pretix_oidc/locale/django.pot
pretix_oidc/locale/de/LC_MESSAGES/django.mo
pretix_oidc/locale/de/LC_MESSAGES/django.po
pretix_oidc/locale/de_Informal/.gitkeep
pretix_oidc/locale/de_Informal/LC_MESSAGES/django.mo
pretix_oidc/locale/de_Informal/LC_MESSAGES/django.po
pretix_oidc/migrations/0001_initial.py
pretix_oidc/migrations/0002_auto_20200919_2030.py
pretix_oidc/migrations/__init__.py
pretix_oidc/static/pretix_oidc/.gitkeep
pretix_oidc/templates/pretix_oidc/.gitkeep
pretix_oidc/templates/pretix_oidc/oidc_assignment_rule_delete.html
pretix_oidc/templates/pretix_oidc/oidc_assignment_rule_edit.html
pretix_oidc/templates/pretix_oidc/oidc_assignment_rules.html
pretix_oidc-2.3.1.dist-info/licenses/LICENSE
pretix_oidc-2.3.1.dist-info/METADATA
pretix_oidc-2.3.1.dist-info/WHEEL
pretix_oidc-2.3.1.dist-info/entry_points.txt
pretix_oidc-2.3.1.dist-info/top_level.txt
pretix_oidc-2.3.1.dist-info/RECORD
