Metadata-Version: 2.4
Name: pretix-oidc
Version: 2.3.1
Summary: OIDC authentication plugin for pretix
Author: Jaakko Rinta-Filppula
Author-email: Felix Schäfer <admin@kif.rocks>
Maintainer-email: Felix Schäfer <admin@kif.rocks>
License-Expression: Apache-2.0
Project-URL: Homepage, https://gitlab.fachschaften.org/kif/pretix-oidc
Project-URL: Repository, https://github.com/thegcat/pretix-oidc
Project-URL: Tracker, https://github.com/thegcat/pretix-oidc/issues
Project-URL: pretix Marketplace, https://marketplace.pretix.eu/products/oidc/
Keywords: pretix,oidc
License-File: LICENSE
Requires-Dist: dictlib
Requires-Dist: oic
Dynamic: license-file
